{
  "library": "tsl26",
  "generatedAt": "2026-05-07T10:14:58.849Z",
  "total": 1,
  "records": [
    {
      "id": "tsl_kickflip",
      "name": "Kickflip",
      "cdnslug": "kickflip",
      "youtubeId": "tnpLkUQZODc",
      "youtubeUrl": "https://www.youtube.com/embed/tnpLkUQZODc?autoplay=1",
      "sourcePath": "/Users/iagolast/Workspace/trainerstudio-static/scripts/tsl26/source/videos/tsl_kickflip_kickflip_source.mp4",
      "clipPath": "/Users/iagolast/Workspace/trainerstudio-static/libraries/tsl26/kickflip/source/kickflip.mp4",
      "sourceDownloaded": true,
      "clipBuilt": true,
      "lastProcessedAt": "2026-05-07T10:14:58.849Z",
      "error": null
    }
  ]
}
